gradiologin/__init__.py
gradiologin/button.py
gradiologin/functions.py
gradiologin/middleware.py
gradiologin/oauth.py
gradiologin/register.py
gradiologin/routes.py
gradiologin/templates/index.template.html
gradiologin-0.1.0.dist-info/LICENSE
gradiologin-0.1.0.dist-info/METADATA
gradiologin-0.1.0.dist-info/WHEEL
gradiologin-0.1.0.dist-info/top_level.txt
gradiologin-0.1.0.dist-info/RECORD
