Metadata-Version: 2.2
Name: gradiologin
Version: 0.1.0
Summary: OAuth Login for Gradio
License: MIT
Project-URL: Homepage, https://github.com/jakjus/gradiologin
Keywords: gradio,login,oauth,authorization,authentication,auth
Requires-Python: >=3.8
License-File: LICENSE
Requires-Dist: gradio>=4.24
Requires-Dist: authlib
Requires-Dist: itsdangerous
